{"OutputFileHashSum":"ECF852090512EA16E8E025957A689D8E019E5170175B4F3214A77DD4089B3EA8","Converted":true,"OutputModifyDate":"2023-11-24T17:49:33.3055073Z","Metadatas":[],"MetadataTypes":[{"CategoryName":"VuGen.Replay","MetadataTypeName":"HP.LR.Vugen.Iteration","Id":1},{"CategoryName":"VuGen.Replay","MetadataTypeName":"HP.LR.Vugen.NotifyTransaction","Id":2},{"CategoryName":"VuGen.Replay","MetadataTypeName":"HP.LR.Vugen.NotifySavingParameter","Id":3},{"CategoryName":"VuGen.Replay","MetadataTypeName":"HP.LR.Vugen.NotifyParameterSubstitution","Id":4},{"CategoryName":"VuGen.Replay","MetadataTypeName":"HP.LR.Vugen.NotifyAny","Id":5},{"CategoryName":"VuGen.Replay","MetadataTypeName":"Utt.Debugger.Error","Id":6}]}